{
  "games": [
    {
      "id": "gba-unbound",
      "title": "Pokémon Unbound",
      "system": "gba",
      "year": 2018,
      "genre": "RPG",
      "region": "Hack",
      "cover": "covers/pokemon-unbound.jpg",
      "rom": "roms/gba/pokemon-unbound.gba",
      "description": "A feature-rich GBA ROM hack with a custom region, QoL, and endgame content."
    },
    {
      "id": "gba-radicalred",
      "title": "Pokémon Radical Red",
      "system": "gba",
      "year": 2020,
      "genre": "RPG",
      "region": "Hack",
      "cover": "covers/pokemon-radicalred.jpg",
      "rom": "roms/gba/pokemon-radicalred.gba",
      "description": "Difficulty-focused FireRed-based hack with modern mechanics."
    },
    {
      "id": "gba-gaia",
      "title": "Pokémon Gaia",
      "system": "gba",
      "year": 2018,
      "genre": "RPG",
      "region": "Hack",
      "cover": "covers/pokemon-gaia.jpg",
      "rom": "roms/gba/pokemon-gaia.gba",
      "description": "Explore the Orbtus region with revamped mechanics and dungeons."
    },
    {
      "id": "gba-rowe",
      "title": "Pokémon R.O.W.E.",
      "system": "gba",
      "year": 2020,
      "genre": "RPG",
      "region": "Hack",
      "cover": "covers/pokemon-rowe.jpg",
      "rom": "roms/gba/pokemon-rowe.gba",
      "description": "Open world hack with scalable levels and extensive customizations."
    },
    {
      "id": "gba-redchapter",
      "title": "Pokémon Adventure — Red Chapter",
      "system": "gba",
      "year": 2014,
      "genre": "RPG",
      "region": "Hack",
      "cover": "covers/pokemon-redchapter.jpg",
      "rom": "roms/gba/pokemon-redchapter.gba",
      "description": "Story-driven hack inspired by the Pokémon Adventures manga."
    },

    {
      "id": "snes-smw",
      "title": "Super Mario World",
      "system": "snes",
      "year": 1990,
      "genre": "Platformer",
      "region": "USA",
      "cover": "covers/smw.png",
      "rom": "roms/snes/smw.sfc",
      "description": "Mario and Yoshi team up across Dinosaur Land in this SNES classic."
    },

    {
      "id": "a26-pitfall",
      "title": "Pitfall!",
      "system": "atari2600",
      "year": 1982,
      "genre": "Platformer",
      "region": "USA",
      "cover": "covers/pitfall.jpg",
      "rom": "roms/atari2600/pitfall.a26",
      "description": "Dodge pits and swing on vines in Activision’s legendary Atari adventure."
    },

    {
      "id": "byor",
      "title": "Bring Your Own ROM",
      "system": "custom",
      "year": "",
      "genre": "",
      "region": "",
      "cover": "assets/byor-cover.svg",
      "rom": ""
    }
  ]
}
